<?xml version="1.0" encoding="UTF-8"?><zwfRoot xmlns:xsi="http://www.w3.org/2001/XMLSchema-instance" xsi:noNamespaceSchemaLocation="testxsd.xsd"><zwfInfo><master><zid>ms013h0000000006</zid><id>style_px</id><name>style_px</name><type>appanage</type><notes>プロパティ項目でstyleに関係があるもの且つピクセル指定の物</notes><scopeZid>ms002h0000000001</scopeZid><heirZif_list></heirZif_list><deficiencyZifZid_list></deficiencyZifZid_list><tag_list></tag_list></master></zwfInfo><zwfFileInfo><lasmsodified><accountZid>ach0000000000001</accountZid><date>20121212 12:12:12.333</date></lasmsodified></zwfFileInfo></zwfRoot>